postcar/__about__.py
postcar/__init__.py
postcar/__main__.py
postcar/_types.py
postcar/errors.py
postcar/py.typed
postcar/cli/__init__.py
postcar/cli/_config.py
postcar/cli/_parser.py
postcar/cli/_types.py
postcar/cli/migrate.py
postcar/config/__init__.py
postcar/config/common.py
postcar/config/database.py
postcar/config/defaults.py
postcar/db/__init__.py
postcar/db/connections.py
postcar/db/lookups.py
postcar/db/queries.py
postcar/db/migrations/__init__.py
postcar/db/migrations/classes.py
postcar/db/migrations/operations.py
postcar/db/migrations/versions.py
postcar/utils/__init__.py
postcar/utils/fs.py
postcar/utils/names.py
postcar-0.0.9.dist-info/METADATA
postcar-0.0.9.dist-info/WHEEL
postcar-0.0.9.dist-info/entry_points.txt
postcar-0.0.9.dist-info/licenses/LICENSE.txt
postcar-0.0.9.dist-info/RECORD
