Metadata-Version: 2.4
Name: postcar
Version: 0.0.9
Summary: A database migration utility for Postgres
Project-URL: Documentation, https://github.com/tunnelworks/postcar#readme
Project-URL: Issues, https://github.com/tunnelworks/postcar/issues
Project-URL: Source, https://github.com/tunnelworks/postcar
Author-email: tunnelworks <git@tunnelworks.org>
License-Expression: Apache-2.0
License-File: LICENSE.txt
Classifier: Development Status :: 2 - Pre-Alpha
Classifier: Programming Language :: Python
Classifier: Programming Language :: Python :: 3.10
Classifier: Programming Language :: Python :: 3.11
Classifier: Programming Language :: Python :: 3.12
Classifier: Programming Language :: Python :: 3.13
Classifier: Programming Language :: Python :: Implementation :: CPython
Classifier: Topic :: Database
Classifier: Typing :: Typed
Requires-Python: >=3.10
Requires-Dist: psycopg>=3
